defectdojo_api_generated/__init__.py
defectdojo_api_generated/api_client.py
defectdojo_api_generated/api_response.py
defectdojo_api_generated/client.py
defectdojo_api_generated/configuration.py
defectdojo_api_generated/exceptions.py
defectdojo_api_generated/helpers.py
defectdojo_api_generated/rest.py
defectdojo_api_generated/api/__init__.py
defectdojo_api_generated/api/announcements_api.py
defectdojo_api_generated/api/api_token_auth_api.py
defectdojo_api_generated/api/configuration_permissions_api.py
defectdojo_api_generated/api/credential_mappings_api.py
defectdojo_api_generated/api/credentials_api.py
defectdojo_api_generated/api/development_environments_api.py
defectdojo_api_generated/api/dojo_group_members_api.py
defectdojo_api_generated/api/dojo_groups_api.py
defectdojo_api_generated/api/endpoint_meta_import_api.py
defectdojo_api_generated/api/endpoint_status_api.py
defectdojo_api_generated/api/endpoints_api.py
defectdojo_api_generated/api/engagement_presets_api.py
defectdojo_api_generated/api/engagements_api.py
defectdojo_api_generated/api/finding_templates_api.py
defectdojo_api_generated/api/findings_api.py
defectdojo_api_generated/api/global_roles_api.py
defectdojo_api_generated/api/import_languages_api.py
defectdojo_api_generated/api/import_scan_api.py
defectdojo_api_generated/api/jira_configurations_api.py
defectdojo_api_generated/api/jira_finding_mappings_api.py
defectdojo_api_generated/api/jira_instances_api.py
defectdojo_api_generated/api/jira_product_configurations_api.py
defectdojo_api_generated/api/jira_projects_api.py
defectdojo_api_generated/api/language_types_api.py
defectdojo_api_generated/api/languages_api.py
defectdojo_api_generated/api/metadata_api.py
defectdojo_api_generated/api/network_locations_api.py
defectdojo_api_generated/api/note_type_api.py
defectdojo_api_generated/api/notes_api.py
defectdojo_api_generated/api/notification_webhooks_api.py
defectdojo_api_generated/api/notifications_api.py
defectdojo_api_generated/api/oa3_api.py
defectdojo_api_generated-0.1.2.dist-info/licenses/LICENSE
defectdojo_api_generated-0.1.2.dist-info/METADATA
defectdojo_api_generated-0.1.2.dist-info/WHEEL
defectdojo_api_generated-0.1.2.dist-info/top_level.txt
defectdojo_api_generated-0.1.2.dist-info/RECORD
