Metadata-Version: 2.4
Name: defectdojo-api-generated
Version: 0.1.2
Summary: Python library to interact with DefectDojo - generated from OpenAPI
Author-email: Filipe Pina <shelf-corncob-said@duck.com>
Project-URL: Homepage, https://github.com/fopina/defectdojo-api-generated
Requires-Python: <4,>=3.9
License-File: LICENSE
Requires-Dist: pydantic>=2
Requires-Dist: python-dateutil>=2.8.2
Requires-Dist: urllib3<3.0.0,>=2.1.0
Requires-Dist: typing-extensions>=4.7.1
Dynamic: license-file
